{
  "portfolio": "こんにちは、私の名前は Adiel Grazt",
  "by": "成長を促進し、ユーザーエクスペリエンスを向上させ、現在のデジタル製品に付加価値を与える戦略的ウェブサイトおよびウェブアプリケーションの設計と開発。",
  "sobreMi": "私について",
  "habilidades": "スキル",
  "proyectos": "プロジェクト",
  "contacto": "連絡先",
  "quienSoy": "私について",
  "descripcionQuienSoy": "私は、テクノロジーとビデオゲームに強い情熱を持ち、プログラミングの世界に入ったばかりのウェブ開発者です。入社してまだ日が浅いですが、日々勉強に励み、良いやり方を一から実践しています。",
  "miEnfoque": "私のアプローチ",
  "descripcionMiEnfoque": "私は、クリーンで、機能的で、速く、意味のあるソリューションを構築することに重点を置いています。プログラミングはコードを超えたものであり、ユーザーエクスペリエンス、デザインの明快さ、プロジェクトのロジックについて考えなければなりません。",
  "valoresDefinen": "私を定義する価値観",
  "compromiso": "コミットメントと責任",
  "ganasDeAprender": "常に学び続ける意欲",
  "profesionalismo": "最初の日からプロフェッショナリズム",
  "creatividad": "実践的なアプローチでの創造性",
  "miObjetivo": "私の目標",
  "descripcionMiObjetivo": "情熱と忍耐力を持ち、常に将来のビジョンを持って仕事に取り組み、どのようなチームにも付加価値を与えることができるプロの開発者になること。",
  "volverAlInicio": "ホームに戻る",
  "descripcionHabilidades": "これは、私が持っているスキルとプログラミングで使用する言語です。",
  "descripcionContacto": "Discordまたは以下のフォームからご連絡ください。",
  "discord": "私のDiscord",
  "nombrePlaceholder": "あなたの名前",
  "correoPlaceholder": "あなたのメールアドレス",
  "mensajePlaceholder": "あなたのメッセージ",
  "enviar": "メッセージを送信",
  "mensajeEnviado": "メッセージが正常に送信されました！",
  "errorEnvio": "メッセージの送信中にエラーが発生しました。もう一度お試しください。",
  "copyright": "© 2025 すべての権利を保有",
  "footerHofsito": "Hofsito によって作成されました",
  "mis_proyectos": "私のプロジェクト",
  "proyecto_1": "プロジェクト1",
  "proyecto_2": "プロジェクト2",
  "proyecto_3": "プロジェクト3",
  "descripcion": "プロジェクトの簡単な説明。",
  "contacto_message": "多くのプロジェクトの最初になりたい場合は、お気軽にお問い合わせください。",
  "descripcionProyecto": "私が関わったすべてのプロジェクト (今のところはありません)",
  "whatsappPlaceholder": "WhatsApp 番号 (プレフィックス付き)",
  "solucionesTitulo": "あなたのために何を作れる？",
  "descripcionSoluciones": "プログラミングの知識がなくてもご安心ください。ゼロから構築できるソリューション例は次のとおりです：",
  "solucionBlogs": "ブログ・ニュースサイト",
  "solucionTiendas": "オンラインストア（EC）",
  "solucionLanding": "高コンバージョンのランディングページ",
  "solucionPortafolio": "個人／エージェンシー向けポートフォリオ",
  "solucionCorporativas": "コーポレートサイト",
  "solucionForos": "フォーラム・コミュニティ",
  "solucionCatalogos": "商品カタログ",
  "solucionReservas": "予約・アポイントシステム",
  "solucionEventos": "イベントページ",
  "solucionNewsletters": "ニュースレター・メーリングリスト"
}


